improvmxpy/__init__.py
improvmxpy/asynchronous/__init__.py
improvmxpy/block/__init__.py
improvmxpy-1.1.dist-info/LICENSE
improvmxpy-1.1.dist-info/METADATA
improvmxpy-1.1.dist-info/WHEEL
improvmxpy-1.1.dist-info/top_level.txt
improvmxpy-1.1.dist-info/RECORD
