Metadata-Version: 2.1
Name: improvmxpy
Version: 1.1
Summary: A ImprovMX API Wrapper!
Home-page: https://github.com/dumb-stuff/improvmx_py
Author: Rukchad Wongprayoon
Author-email: contact@biomooping.tk
License: MIT
Project-URL: Documentation, https://improvmxpy.tk
Project-URL: Github Repository, https://github.com/dumb-stuff/improvmx_py
Project-URL: Issues Reporting, https://github.com/dumb-stuff/improvmx_py/issues
Project-URL: Pull Requests, https://github.com/dumb-stuff/improvmx_py/pullrequests
Project-URL: Discord server, https://discord.gg/sHprKhGwg8
Project-URL: Funny youtube clip, https://www.youtube.com/watch?v=dQw4w9WgXcQ
Keywords: Tools
Platform: UNKNOWN
License-File: LICENSE
Requires-Dist: requests
Requires-Dist: aiohttp
Requires-Dist: cChardet
Requires-Dist: aiodns
